odoo/addons/quality_control_plan/README.rst
odoo/addons/quality_control_plan/__init__.py
odoo/addons/quality_control_plan/__manifest__.py
odoo/addons/quality_control_plan/i18n/it.po
odoo/addons/quality_control_plan/i18n/quality_control_plan.pot
odoo/addons/quality_control_plan/models/__init__.py
odoo/addons/quality_control_plan/models/mgmtsystem_nonconformity_inspection.py
odoo/addons/quality_control_plan/models/partner_quality.py
odoo/addons/quality_control_plan/models/product_trigger.py
odoo/addons/quality_control_plan/models/qc_inspection_plan.py
odoo/addons/quality_control_plan/models/qc_plan.py
odoo/addons/quality_control_plan/models/qc_trigger.py
odoo/addons/quality_control_plan/models/qc_trigger_partner_line.py
odoo/addons/quality_control_plan/models/stock_picking_inspection.py
odoo/addons/quality_control_plan/readme/CONFIGURE.rst
odoo/addons/quality_control_plan/readme/CONTRIBUTORS.rst
odoo/addons/quality_control_plan/readme/DESCRIPTION.rst
odoo/addons/quality_control_plan/readme/HISTORY.rst
odoo/addons/quality_control_plan/readme/INSTALL.rst
odoo/addons/quality_control_plan/readme/USAGE.rst
odoo/addons/quality_control_plan/security/ir.model.access.csv
odoo/addons/quality_control_plan/static/description/icon.png
odoo/addons/quality_control_plan/static/description/index.html
odoo/addons/quality_control_plan/tests/__init__.py
odoo/addons/quality_control_plan/tests/test_plan.py
odoo/addons/quality_control_plan/views/mgmtsystem_nonconformity_view.xml
odoo/addons/quality_control_plan/views/partner_view.xml
odoo/addons/quality_control_plan/views/product_view.xml
odoo/addons/quality_control_plan/views/qc_inspection_view.xml
odoo/addons/quality_control_plan/views/qc_menu.xml
odoo/addons/quality_control_plan/views/qc_plan_view.xml
odoo11_addon_quality_control_plan-11.0.1.0.0.99.dev5.dist-info/METADATA
odoo11_addon_quality_control_plan-11.0.1.0.0.99.dev5.dist-info/WHEEL
odoo11_addon_quality_control_plan-11.0.1.0.0.99.dev5.dist-info/top_level.txt
odoo11_addon_quality_control_plan-11.0.1.0.0.99.dev5.dist-info/RECORD
