Metadata-Version: 2.1
Name: odoo11-addon-quality-control-plan
Version: 11.0.1.0.0.99.dev5
Summary: Control Plan for Inspection quantity definition.
Home-page: https://gitlab.com/PNLUG/Odoo/management-system-improvements/tree/11.0/quality_control_plan
Author: Associazione PNLUG - Gruppo Odoo, Odoo Community Association (OCA)
Author-email: support@odoo-community.org
License: AGPL-3
Platform: UNKNOWN
Classifier: Programming Language :: Python
Classifier: Framework :: Odoo
Classifier: Framework :: Odoo :: 11.0
Classifier: License :: OSI Approved :: GNU Affero General Public License v3
Requires-Python: >=2.7, !=3.0.*, !=3.1.*, !=3.2.*, !=3.3.*, !=3.4.*
Requires-Dist: odoo11-addon-mgmtsystem
Requires-Dist: odoo11-addon-mgmtsystem-nonconformity
Requires-Dist: odoo11-addon-quality-control
Requires-Dist: odoo11-addon-quality-control-stock
Requires-Dist: odoo <11.1dev,>=11.0a
